torproxy_client/__init__.py
torproxy_client/tor_client.py
torproxy_client-0.1.3.dist-info/licenses/LICENSE
torproxy_client-0.1.3.dist-info/METADATA
torproxy_client-0.1.3.dist-info/WHEEL
torproxy_client-0.1.3.dist-info/top_level.txt
torproxy_client-0.1.3.dist-info/RECORD
