Metadata-Version: 2.4
Name: torproxy_client
Version: 0.1.3
Summary: A simple Python library to connect to the internet through Tor proxy.
Author-email: mi8bi <mi8biiiii@gmail.com>
License-Expression: MIT
Project-URL: Homepage, https://github.com/mi8bi/torproxy_client
Project-URL: Repository, https://github.com/mi8bi/torproxy_client
License-File: LICENSE
Requires-Dist: requests==2.32.3
Requires-Dist: stem==1.8.2
Requires-Dist: PySocks==1.7.1
Dynamic: license-file
